MofanShujuchuliXilieJiaocheng20201031Fix1/README.md
MofanShujuchuliXilieJiaocheng20201031Fix1/__init__.py
MofanShujuchuliXilieJiaocheng20201031Fix1/__main__.py
MofanShujuchuliXilieJiaocheng20201031Fix1/file.epub
MofanShujuchuliXilieJiaocheng20201031Fix1/index.html
MofanShujuchuliXilieJiaocheng20201031Fix1/css/__init__.py
MofanShujuchuliXilieJiaocheng20201031Fix1/css/annotations.css
MofanShujuchuliXilieJiaocheng20201031Fix1/css/main.css
MofanShujuchuliXilieJiaocheng20201031Fix1/css/normalize.css
MofanShujuchuliXilieJiaocheng20201031Fix1/css/popup.css
MofanShujuchuliXilieJiaocheng20201031Fix1/font/__init__.py
MofanShujuchuliXilieJiaocheng20201031Fix1/font/fontello.eot
MofanShujuchuliXilieJiaocheng20201031Fix1/font/fontello.svg
MofanShujuchuliXilieJiaocheng20201031Fix1/font/fontello.ttf
MofanShujuchuliXilieJiaocheng20201031Fix1/font/fontello.woff
MofanShujuchuliXilieJiaocheng20201031Fix1/img/__init__.py
MofanShujuchuliXilieJiaocheng20201031Fix1/img/annotator-glyph-sprite.png
MofanShujuchuliXilieJiaocheng20201031Fix1/img/annotator-icon-sprite.png
MofanShujuchuliXilieJiaocheng20201031Fix1/img/apple-touch-icon.png
MofanShujuchuliXilieJiaocheng20201031Fix1/img/cancelfullscreen.png
MofanShujuchuliXilieJiaocheng20201031Fix1/img/close.png
MofanShujuchuliXilieJiaocheng20201031Fix1/img/fullscreen.png
MofanShujuchuliXilieJiaocheng20201031Fix1/img/loader.gif
MofanShujuchuliXilieJiaocheng20201031Fix1/img/menu-icon.png
MofanShujuchuliXilieJiaocheng20201031Fix1/img/save.png
MofanShujuchuliXilieJiaocheng20201031Fix1/img/saved.png
MofanShujuchuliXilieJiaocheng20201031Fix1/img/settings-s.png
MofanShujuchuliXilieJiaocheng20201031Fix1/img/settings.png
MofanShujuchuliXilieJiaocheng20201031Fix1/img/star.png
MofanShujuchuliXilieJiaocheng20201031Fix1/js/__init__.py
MofanShujuchuliXilieJiaocheng20201031Fix1/js/epub.js
MofanShujuchuliXilieJiaocheng20201031Fix1/js/epub.min.js
MofanShujuchuliXilieJiaocheng20201031Fix1/js/epub.min.map
MofanShujuchuliXilieJiaocheng20201031Fix1/js/hooks.min.js
mofan_shujuchuli_xilie_jiaocheng_2020_10_31_fix1-2025.3.24.1.dist-info/METADATA
mofan_shujuchuli_xilie_jiaocheng_2020_10_31_fix1-2025.3.24.1.dist-info/WHEEL
mofan_shujuchuli_xilie_jiaocheng_2020_10_31_fix1-2025.3.24.1.dist-info/entry_points.txt
mofan_shujuchuli_xilie_jiaocheng_2020_10_31_fix1-2025.3.24.1.dist-info/top_level.txt
mofan_shujuchuli_xilie_jiaocheng_2020_10_31_fix1-2025.3.24.1.dist-info/RECORD
